pylean/__init__.py
pylean-0.0.1a0.dist-info/licenses/LICENSE
pylean-0.0.1a0.dist-info/METADATA
pylean-0.0.1a0.dist-info/WHEEL
pylean-0.0.1a0.dist-info/top_level.txt
pylean-0.0.1a0.dist-info/RECORD
